{
  "slug": "galveston-hurricane-1900",
  "title": "ガルベストンハリケーン（1900年）",
  "titleEn": "1900 Galveston Hurricane",
  "date": "1900-09-08",
  "country": "usa",
  "region": "テキサス州ガルベストン",
  "type": "typhoon",
  "magnitude": null,
  "deaths": 8000,
  "missing": 0,
  "injured": 0,
  "buildings": "約3,600棟全壊",
  "economicLoss": "約3,000万ドル（当時）",
  "summary": "1900年9月8日、カテゴリー4のハリケーンがテキサス州ガルベストン島を直撃。最大風速70m/s・高潮4〜5mが島全体を飲み込み、推定6,000〜12,000人（中央値約8,000人）が死亡した。米国史上最大の自然災害死者数を記録。当時人口37,000人の繁栄した港湾都市が一夜で壊滅した。この教訓から米国の近代的ハリケーン対策・高潮防護システムが構築された。",
  "background": "ガルベストン島は海抜最大約2.7mの低平な砂州島。19世紀末は綿花輸出の中心地として繁栄していたが、海岸沿いの高潮防護施設はなかった。ハリケーン予測技術も未熟で、住民への警告は不十分だった。",
  "socialContext": "20世紀転換期のアメリカ南部。島の人々は以前にも台風被害を経験していたが、大規模な高潮への備えはなかった。政治的・経済的利権から、以前提案されていた高潮対策工事が実施されていなかった。",
  "damage": "島の建物の約半数が全壊・流失。高潮で島全体が水没。死体処理が追いつかず多くの遺体が湾内に投棄された。その後のコレラ発生も懸念されたが大規模感染は避けられた。",
  "lifeline": "電信切断・橋梁流失で本土との連絡が完全に途絶。救援物資の到達に数日を要した。",
  "lessons": [
    "海抜の低い島・半島・砂州は高潮に極めて脆弱。このような地形への無秩序な市街化は大規模被害をもたらす",
    "この惨事を教訓に、米国は高さ5mの防潮堤建設と市街地の嵩上げを実施。1915年のハリケーンでは被害を大幅軽減",
    "ハリケーン予測・警報システムの近代化の直接的な契機となった",
    "低地・沿岸居住者は高潮ハザードマップを必ず確認し、台風接近時は早期退避を徹底する",
    "繁栄と利便性が災害リスク軽視につながる。経済的理由による防災投資の先送りは将来の甚大被害を招く"
  ],
  "preparedness": [
    "海抜の低い沿岸・島に住む場合、高潮ハザードマップで最大浸水深と浸水範囲を確認する",
    "ハリケーン・台風の接近時は早期の内陸退避を優先する。「建物さえ頑丈なら大丈夫」は高潮には通用しない",
    "退避命令（避難指示）が出る前に自主的に避難を開始する判断基準を家族で決めておく",
    "避難車中やホテルでの宿泊を想定した携行品（3日分の食料・水・薬・充電器）を準備する",
    "海抜・地形情報を日本のハザードマップで確認する（国土交通省「重ねるハザードマップ」）"
  ],
  "affiliateCategory": "typhoon",
  "relatedSlugs": [
    "bhola-cyclone-1970",
    "hurricane-katrina-2005",
    "haiyan-typhoon-2013",
    "isewan-typhoon-1959",
    "cyclone-idai-2019"
  ],
  "tags": ["ハリケーン", "高潮", "アメリカ", "テキサス州", "島嶼災害", "20世紀初頭", "1900年"],
  "sources": [
    {"title": "NOAA National Hurricane Center - Galveston Hurricane 1900", "url": "https://www.nhc.noaa.gov/outreach/history/"},
    {"title": "USGS - 1900 Galveston Hurricane"},
    {"title": "Texas State Library and Archives Commission - Galveston Hurricane"}
  ],
  "featured": false,
  "publishedAt": "2026-04-09",
  "updatedAt": "2026-04-09",
  "metaDescription": "ガルベストンハリケーン（1900年）は米国史上最大の約8,000人死亡。低地の島を高潮が壊滅させた歴史と近代高潮対策の原点を解説。"
}
