{
  "slug": "tohoku-earthquake-2011",
  "title": "東日本大震災（2011年）",
  "titleEn": "Great East Japan Earthquake",
  "date": "2011-03-11",
  "country": "japan",
  "region": "東北地方・太平洋沖",
  "type": "earthquake",
  "magnitude": "M9.0",
  "deaths": 15900,
  "missing": 2523,
  "injured": 6157,
  "buildings": "全壊・半壊合わせて約40万棟",
  "economicLoss": "約16.9兆円（内閣府推計）",
  "summary": "2011年3月11日14時46分、宮城県沖を震源とするマグニチュード9.0の巨大地震が発生。国内観測史上最大の地震で、大津波が東北・関東の沿岸を襲い、約1万6千人が犠牲となった。東京電力福島第一原子力発電所の事故も引き起こし、日本の災害史上かつてない複合災害となった。",
  "background": "太平洋プレートが北米プレートの下に沈み込む境界で発生した逆断層型地震。震源域は長さ約450km、幅約200kmに及ぶ広大なもので、最大約10mの断層のずれが巨大津波を引き起こした。",
  "socialContext": "地震発生時、岩手・宮城・福島の沿岸部には漁業・農業を中心とした地域社会が形成されており、多くの住民が日常的に海と接していた。東日本大震災の教訓は、ハザードマップの限界や住民の避難行動の重要性を改めて示した。",
  "damage": "宮城・岩手・福島を中心に、最大遡上高40.1m（岩手県大船渡市）に及ぶ大津波が発生。沿岸部の市街地が壊滅的な被害を受けた。福島第一原発では炉心溶融（メルトダウン）が発生し、放射性物質の大規模な漏えいが起きた。避難者は最大47万人超。",
  "lifeline": "広域停電（約800万戸）、断水（約180万戸）、ガス供給停止が長期化。東北新幹線は約49日間運休。東京電力の計画停電も実施された。",
  "lessons": [
    "「想定外」を想定することの重要性（ハザードマップの限界）",
    "津波てんでんこ（各自が迅速に高台へ逃げる）の実践が生存率を高めた",
    "原子力発電所の津波対策の不備が複合災害を招いた",
    "防潮堤だけに頼らず、住民の避難行動そのものを高める必要がある",
    "災害関連死（震災後の避難生活でなくなる方）対策の重要性",
    "広域物資支援・行政機能の継続性確保の必要性"
  ],
  "preparedness": [
    "自宅・職場・学校それぞれの津波ハザードマップを確認する",
    "避難場所までの複数ルートを実際に歩いて確認する",
    "家族が離れた場所にいても連絡が取れる手段（災害伝言ダイヤル171）を決めておく",
    "3日分（できれば7日分）の水・食料を備蓄する（1人1日3L計算）",
    "停電に備えてポータブル電源・モバイルバッテリーを用意する",
    "避難生活に備えて非常用トイレを準備する"
  ],
  "affiliateCategory": "general",
  "relatedSlugs": [
    "hanshin-awaji-earthquake-1995",
    "noto-earthquake-2024",
    "okushiri-tsunami-1993"
  ],
  "tags": [
    "地震",
    "津波",
    "原子力",
    "東北",
    "複合災害",
    "M9クラス"
  ],
  "sources": [
    {
      "title": "内閣府 東日本大震災の被害・影響",
      "url": "https://www.bousai.go.jp/kohou/kouhoubousai/h23/64/special_01.html"
    },
    {
      "title": "消防庁 東日本大震災記録集"
    },
    {
      "title": "復興庁 復興の現状"
    }
  ],
  "featured": true,
  "publishedAt": "2024-01-01",
  "metaDescription": "東日本大震災（2011年3月11日）の被害・教訓・今に活かす備えを詳しく解説。死者・行方不明者約1万8千人、M9.0の巨大地震と大津波が東北を襲った複合災害の全記録。"
}